<Settings>
<score>0<score/>
<playerNumber>2<playerNumber/>
<aiNumber>0<aiNumber/>
<mapSize>30<mapSize/>
<name>AAA<name/>
<Settings/><mapwall0>
<x>0.000000<x/>
<y>0.000000<y/>
<mapwall0/>
<mapwall1>
<x>0.000000<x/>
<y>1.000000<y/>
<mapwall1/>
<mapwall2>
<x>0.000000<x/>
<y>2.000000<y/>
<mapwall2/>
<mapwall3>
<x>0.000000<x/>
<y>3.000000<y/>
<mapwall3/>
<mapwall4>
<x>0.000000<x/>
<y>4.000000<y/>
<mapwall4/>
<mapwall5>
<x>0.000000<x/>
<y>5.000000<y/>
<mapwall5/>
<mapwall6>
<x>0.000000<x/>
<y>6.000000<y/>
<mapwall6/>
<mapwall7>
<x>0.000000<x/>
<y>7.000000<y/>
<mapwall7/>
<mapwall8>
<x>0.000000<x/>
<y>8.000000<y/>
<mapwall8/>
<mapwall9>
<x>0.000000<x/>
<y>9.000000<y/>
<mapwall9/>
<mapwall10>
<x>0.000000<x/>
<y>10.000000<y/>
<mapwall10/>
<mapwall11>
<x>0.000000<x/>
<y>11.000000<y/>
<mapwall11/>
<mapwall12>
<x>0.000000<x/>
<y>12.000000<y/>
<mapwall12/>
<mapwall13>
<x>0.000000<x/>
<y>13.000000<y/>
<mapwall13/>
<mapwall14>
<x>0.000000<x/>
<y>14.000000<y/>
<mapwall14/>
<mapwall15>
<x>0.000000<x/>
<y>15.000000<y/>
<mapwall15/>
<mapwall16>
<x>0.000000<x/>
<y>16.000000<y/>
<mapwall16/>
<mapwall17>
<x>0.000000<x/>
<y>17.000000<y/>
<mapwall17/>
<mapwall18>
<x>0.000000<x/>
<y>18.000000<y/>
<mapwall18/>
<mapwall19>
<x>0.000000<x/>
<y>19.000000<y/>
<mapwall19/>
<mapwall20>
<x>0.000000<x/>
<y>20.000000<y/>
<mapwall20/>
<mapwall21>
<x>0.000000<x/>
<y>21.000000<y/>
<mapwall21/>
<mapwall22>
<x>0.000000<x/>
<y>22.000000<y/>
<mapwall22/>
<mapwall23>
<x>0.000000<x/>
<y>23.000000<y/>
<mapwall23/>
<mapwall24>
<x>0.000000<x/>
<y>24.000000<y/>
<mapwall24/>
<mapwall25>
<x>0.000000<x/>
<y>25.000000<y/>
<mapwall25/>
<mapwall26>
<x>0.000000<x/>
<y>26.000000<y/>
<mapwall26/>
<mapwall27>
<x>0.000000<x/>
<y>27.000000<y/>
<mapwall27/>
<mapwall28>
<x>0.000000<x/>
<y>28.000000<y/>
<mapwall28/>
<mapwall29>
<x>0.000000<x/>
<y>29.000000<y/>
<mapwall29/>
<mapwall30>
<x>1.000000<x/>
<y>0.000000<y/>
<mapwall30/>
<brkwall0>
<x>1.000000<x/>
<y>1.000000<y/>
<brkwall0/>
<brkwall1>
<x>1.000000<x/>
<y>2.000000<y/>
<brkwall1/>
<brkwall2>
<x>1.000000<x/>
<y>3.000000<y/>
<brkwall2/>
<brkwall3>
<x>1.000000<x/>
<y>4.000000<y/>
<brkwall3/>
<brkwall4>
<x>1.000000<x/>
<y>5.000000<y/>
<brkwall4/>
<brkwall5>
<x>1.000000<x/>
<y>6.000000<y/>
<brkwall5/>
<brkwall6>
<x>1.000000<x/>
<y>7.000000<y/>
<brkwall6/>
<brkwall7>
<x>1.000000<x/>
<y>8.000000<y/>
<brkwall7/>
<brkwall8>
<x>1.000000<x/>
<y>9.000000<y/>
<brkwall8/>
<brkwall9>
<x>1.000000<x/>
<y>10.000000<y/>
<brkwall9/>
<brkwall10>
<x>1.000000<x/>
<y>11.000000<y/>
<brkwall10/>
<floor0>
<x>1.000000<x/>
<y>12.000000<y/>
<floor0/>
<brkwall11>
<x>1.000000<x/>
<y>13.000000<y/>
<brkwall11/>
<brkwall12>
<x>1.000000<x/>
<y>14.000000<y/>
<brkwall12/>
<floor1>
<x>1.000000<x/>
<y>15.000000<y/>
<floor1/>
<brkwall13>
<x>1.000000<x/>
<y>16.000000<y/>
<brkwall13/>
<floor2>
<x>1.000000<x/>
<y>17.000000<y/>
<floor2/>
<brkwall14>
<x>1.000000<x/>
<y>18.000000<y/>
<brkwall14/>
<floor3>
<x>1.000000<x/>
<y>19.000000<y/>
<floor3/>
<floor4>
<x>1.000000<x/>
<y>20.000000<y/>
<floor4/>
<floor5>
<x>1.000000<x/>
<y>21.000000<y/>
<floor5/>
<brkwall15>
<x>1.000000<x/>
<y>22.000000<y/>
<brkwall15/>
<brkwall16>
<x>1.000000<x/>
<y>23.000000<y/>
<brkwall16/>
<floor6>
<x>1.000000<x/>
<y>24.000000<y/>
<floor6/>
<floor7>
<x>1.000000<x/>
<y>25.000000<y/>
<floor7/>
<floor8>
<x>1.000000<x/>
<y>26.000000<y/>
<floor8/>
<brkwall17>
<x>1.000000<x/>
<y>27.000000<y/>
<brkwall17/>
<floor9>
<x>1.000000<x/>
<y>28.000000<y/>
<floor9/>
<mapwall31>
<x>1.000000<x/>
<y>29.000000<y/>
<mapwall31/>
<mapwall32>
<x>2.000000<x/>
<y>0.000000<y/>
<mapwall32/>
<brkwall18>
<x>2.000000<x/>
<y>1.000000<y/>
<brkwall18/>
<brkwall19>
<x>2.000000<x/>
<y>2.000000<y/>
<brkwall19/>
<ubrkwall0>
<x>2.000000<x/>
<y>3.000000<y/>
<ubrkwall0/>
<floor10>
<x>2.000000<x/>
<y>4.000000<y/>
<floor10/>
<brkwall20>
<x>2.000000<x/>
<y>5.000000<y/>
<brkwall20/>
<ubrkwall1>
<x>2.000000<x/>
<y>6.000000<y/>
<ubrkwall1/>
<brkwall21>
<x>2.000000<x/>
<y>7.000000<y/>
<brkwall21/>
<ubrkwall2>
<x>2.000000<x/>
<y>8.000000<y/>
<ubrkwall2/>
<brkwall22>
<x>2.000000<x/>
<y>9.000000<y/>
<brkwall22/>
<brkwall23>
<x>2.000000<x/>
<y>10.000000<y/>
<brkwall23/>
<ubrkwall3>
<x>2.000000<x/>
<y>11.000000<y/>
<ubrkwall3/>
<ubrkwall4>
<x>2.000000<x/>
<y>12.000000<y/>
<ubrkwall4/>
<ubrkwall5>
<x>2.000000<x/>
<y>13.000000<y/>
<ubrkwall5/>
<brkwall24>
<x>2.000000<x/>
<y>14.000000<y/>
<brkwall24/>
<ubrkwall6>
<x>2.000000<x/>
<y>15.000000<y/>
<ubrkwall6/>
<floor11>
<x>2.000000<x/>
<y>16.000000<y/>
<floor11/>
<ubrkwall7>
<x>2.000000<x/>
<y>17.000000<y/>
<ubrkwall7/>
<brkwall25>
<x>2.000000<x/>
<y>18.000000<y/>
<brkwall25/>
<ubrkwall8>
<x>2.000000<x/>
<y>19.000000<y/>
<ubrkwall8/>
<floor12>
<x>2.000000<x/>
<y>20.000000<y/>
<floor12/>
<ubrkwall9>
<x>2.000000<x/>
<y>21.000000<y/>
<ubrkwall9/>
<ubrkwall10>
<x>2.000000<x/>
<y>22.000000<y/>
<ubrkwall10/>
<brkwall26>
<x>2.000000<x/>
<y>23.000000<y/>
<brkwall26/>
<floor13>
<x>2.000000<x/>
<y>24.000000<y/>
<floor13/>
<ubrkwall11>
<x>2.000000<x/>
<y>25.000000<y/>
<ubrkwall11/>
<ubrkwall12>
<x>2.000000<x/>
<y>26.000000<y/>
<ubrkwall12/>
<floor14>
<x>2.000000<x/>
<y>27.000000<y/>
<floor14/>
<brkwall27>
<x>2.000000<x/>
<y>28.000000<y/>
<brkwall27/>
<mapwall33>
<x>2.000000<x/>
<y>29.000000<y/>
<mapwall33/>
<mapwall34>
<x>3.000000<x/>
<y>0.000000<y/>
<mapwall34/>
<brkwall28>
<x>3.000000<x/>
<y>1.000000<y/>
<brkwall28/>
<floor15>
<x>3.000000<x/>
<y>2.000000<y/>
<floor15/>
<brkwall29>
<x>3.000000<x/>
<y>3.000000<y/>
<brkwall29/>
<floor16>
<x>3.000000<x/>
<y>4.000000<y/>
<floor16/>
<floor17>
<x>3.000000<x/>
<y>5.000000<y/>
<floor17/>
<floor18>
<x>3.000000<x/>
<y>6.000000<y/>
<floor18/>
<floor19>
<x>3.000000<x/>
<y>7.000000<y/>
<floor19/>
<floor20>
<x>3.000000<x/>
<y>8.000000<y/>
<floor20/>
<floor21>
<x>3.000000<x/>
<y>9.000000<y/>
<floor21/>
<ubrkwall13>
<x>3.000000<x/>
<y>10.000000<y/>
<ubrkwall13/>
<ubrkwall14>
<x>3.000000<x/>
<y>11.000000<y/>
<ubrkwall14/>
<floor22>
<x>3.000000<x/>
<y>12.000000<y/>
<floor22/>
<brkwall30>
<x>3.000000<x/>
<y>13.000000<y/>
<brkwall30/>
<floor23>
<x>3.000000<x/>
<y>14.000000<y/>
<floor23/>
<ubrkwall15>
<x>3.000000<x/>
<y>15.000000<y/>
<ubrkwall15/>
<brkwall31>
<x>3.000000<x/>
<y>16.000000<y/>
<brkwall31/>
<brkwall32>
<x>3.000000<x/>
<y>17.000000<y/>
<brkwall32/>
<floor24>
<x>3.000000<x/>
<y>18.000000<y/>
<floor24/>
<brkwall33>
<x>3.000000<x/>
<y>19.000000<y/>
<brkwall33/>
<ubrkwall16>
<x>3.000000<x/>
<y>20.000000<y/>
<ubrkwall16/>
<floor25>
<x>3.000000<x/>
<y>21.000000<y/>
<floor25/>
<floor26>
<x>3.000000<x/>
<y>22.000000<y/>
<floor26/>
<brkwall34>
<x>3.000000<x/>
<y>23.000000<y/>
<brkwall34/>
<brkwall35>
<x>3.000000<x/>
<y>24.000000<y/>
<brkwall35/>
<brkwall36>
<x>3.000000<x/>
<y>25.000000<y/>
<brkwall36/>
<brkwall37>
<x>3.000000<x/>
<y>26.000000<y/>
<brkwall37/>
<ubrkwall17>
<x>3.000000<x/>
<y>27.000000<y/>
<ubrkwall17/>
<floor27>
<x>3.000000<x/>
<y>28.000000<y/>
<floor27/>
<mapwall35>
<x>3.000000<x/>
<y>29.000000<y/>
<mapwall35/>
<mapwall36>
<x>4.000000<x/>
<y>0.000000<y/>
<mapwall36/>
<floor28>
<x>4.000000<x/>
<y>1.000000<y/>
<floor28/>
<brkwall38>
<x>4.000000<x/>
<y>2.000000<y/>
<brkwall38/>
<ubrkwall18>
<x>4.000000<x/>
<y>3.000000<y/>
<ubrkwall18/>
<brkwall39>
<x>4.000000<x/>
<y>4.000000<y/>
<brkwall39/>
<floor29>
<x>4.000000<x/>
<y>5.000000<y/>
<floor29/>
<ubrkwall19>
<x>4.000000<x/>
<y>6.000000<y/>
<ubrkwall19/>
<floor30>
<x>4.000000<x/>
<y>7.000000<y/>
<floor30/>
<floor31>
<x>4.000000<x/>
<y>8.000000<y/>
<floor31/>
<ubrkwall20>
<x>4.000000<x/>
<y>9.000000<y/>
<ubrkwall20/>
<floor32>
<x>4.000000<x/>
<y>10.000000<y/>
<floor32/>
<brkwall40>
<x>4.000000<x/>
<y>11.000000<y/>
<brkwall40/>
<floor33>
<x>4.000000<x/>
<y>12.000000<y/>
<floor33/>
<floor34>
<x>4.000000<x/>
<y>13.000000<y/>
<floor34/>
<brkwall41>
<x>4.000000<x/>
<y>14.000000<y/>
<brkwall41/>
<brkwall42>
<x>4.000000<x/>
<y>15.000000<y/>
<brkwall42/>
<brkwall43>
<x>4.000000<x/>
<y>16.000000<y/>
<brkwall43/>
<ubrkwall21>
<x>4.000000<x/>
<y>17.000000<y/>
<ubrkwall21/>
<floor35>
<x>4.000000<x/>
<y>18.000000<y/>
<floor35/>
<floor36>
<x>4.000000<x/>
<y>19.000000<y/>
<floor36/>
<ubrkwall22>
<x>4.000000<x/>
<y>20.000000<y/>
<ubrkwall22/>
<floor37>
<x>4.000000<x/>
<y>21.000000<y/>
<floor37/>
<ubrkwall23>
<x>4.000000<x/>
<y>22.000000<y/>
<ubrkwall23/>
<floor38>
<x>4.000000<x/>
<y>23.000000<y/>
<floor38/>
<ubrkwall24>
<x>4.000000<x/>
<y>24.000000<y/>
<ubrkwall24/>
<ubrkwall25>
<x>4.000000<x/>
<y>25.000000<y/>
<ubrkwall25/>
<brkwall44>
<x>4.000000<x/>
<y>26.000000<y/>
<brkwall44/>
<brkwall45>
<x>4.000000<x/>
<y>27.000000<y/>
<brkwall45/>
<floor39>
<x>4.000000<x/>
<y>28.000000<y/>
<floor39/>
<mapwall37>
<x>4.000000<x/>
<y>29.000000<y/>
<mapwall37/>
<mapwall38>
<x>5.000000<x/>
<y>0.000000<y/>
<mapwall38/>
<brkwall46>
<x>5.000000<x/>
<y>1.000000<y/>
<brkwall46/>
<floor40>
<x>5.000000<x/>
<y>2.000000<y/>
<floor40/>
<floor41>
<x>5.000000<x/>
<y>3.000000<y/>
<floor41/>
<ubrkwall26>
<x>5.000000<x/>
<y>4.000000<y/>
<ubrkwall26/>
<ubrkwall27>
<x>5.000000<x/>
<y>5.000000<y/>
<ubrkwall27/>
<ubrkwall28>
<x>5.000000<x/>
<y>6.000000<y/>
<ubrkwall28/>
<brkwall47>
<x>5.000000<x/>
<y>7.000000<y/>
<brkwall47/>
<ubrkwall29>
<x>5.000000<x/>
<y>8.000000<y/>
<ubrkwall29/>
<ubrkwall30>
<x>5.000000<x/>
<y>9.000000<y/>
<ubrkwall30/>
<floor42>
<x>5.000000<x/>
<y>10.000000<y/>
<floor42/>
<ubrkwall31>
<x>5.000000<x/>
<y>11.000000<y/>
<ubrkwall31/>
<floor43>
<x>5.000000<x/>
<y>12.000000<y/>
<floor43/>
<ubrkwall32>
<x>5.000000<x/>
<y>13.000000<y/>
<ubrkwall32/>
<brkwall48>
<x>5.000000<x/>
<y>14.000000<y/>
<brkwall48/>
<floor44>
<x>5.000000<x/>
<y>15.000000<y/>
<floor44/>
<brkwall49>
<x>5.000000<x/>
<y>16.000000<y/>
<brkwall49/>
<floor45>
<x>5.000000<x/>
<y>17.000000<y/>
<floor45/>
<floor46>
<x>5.000000<x/>
<y>18.000000<y/>
<floor46/>
<ubrkwall33>
<x>5.000000<x/>
<y>19.000000<y/>
<ubrkwall33/>
<brkwall50>
<x>5.000000<x/>
<y>20.000000<y/>
<brkwall50/>
<ubrkwall34>
<x>5.000000<x/>
<y>21.000000<y/>
<ubrkwall34/>
<ubrkwall35>
<x>5.000000<x/>
<y>22.000000<y/>
<ubrkwall35/>
<floor47>
<x>5.000000<x/>
<y>23.000000<y/>
<floor47/>
<brkwall51>
<x>5.000000<x/>
<y>24.000000<y/>
<brkwall51/>
<brkwall52>
<x>5.000000<x/>
<y>25.000000<y/>
<brkwall52/>
<ubrkwall36>
<x>5.000000<x/>
<y>26.000000<y/>
<ubrkwall36/>
<ubrkwall37>
<x>5.000000<x/>
<y>27.000000<y/>
<ubrkwall37/>
<floor48>
<x>5.000000<x/>
<y>28.000000<y/>
<floor48/>
<mapwall39>
<x>5.000000<x/>
<y>29.000000<y/>
<mapwall39/>
<mapwall40>
<x>6.000000<x/>
<y>0.000000<y/>
<mapwall40/>
<floor49>
<x>6.000000<x/>
<y>1.000000<y/>
<floor49/>
<ubrkwall38>
<x>6.000000<x/>
<y>2.000000<y/>
<ubrkwall38/>
<brkwall53>
<x>6.000000<x/>
<y>3.000000<y/>
<brkwall53/>
<brkwall54>
<x>6.000000<x/>
<y>4.000000<y/>
<brkwall54/>
<floor50>
<x>6.000000<x/>
<y>5.000000<y/>
<floor50/>
<floor51>
<x>6.000000<x/>
<y>6.000000<y/>
<floor51/>
<floor52>
<x>6.000000<x/>
<y>7.000000<y/>
<floor52/>
<brkwall55>
<x>6.000000<x/>
<y>8.000000<y/>
<brkwall55/>
<floor53>
<x>6.000000<x/>
<y>9.000000<y/>
<floor53/>
<brkwall56>
<x>6.000000<x/>
<y>10.000000<y/>
<brkwall56/>
<floor54>
<x>6.000000<x/>
<y>11.000000<y/>
<floor54/>
<floor55>
<x>6.000000<x/>
<y>12.000000<y/>
<floor55/>
<ubrkwall39>
<x>6.000000<x/>
<y>13.000000<y/>
<ubrkwall39/>
<floor56>
<x>6.000000<x/>
<y>14.000000<y/>
<floor56/>
<floor57>
<x>6.000000<x/>
<y>15.000000<y/>
<floor57/>
<brkwall57>
<x>6.000000<x/>
<y>16.000000<y/>
<brkwall57/>
<floor58>
<x>6.000000<x/>
<y>17.000000<y/>
<floor58/>
<floor59>
<x>6.000000<x/>
<y>18.000000<y/>
<floor59/>
<ubrkwall40>
<x>6.000000<x/>
<y>19.000000<y/>
<ubrkwall40/>
<ubrkwall41>
<x>6.000000<x/>
<y>20.000000<y/>
<ubrkwall41/>
<brkwall58>
<x>6.000000<x/>
<y>21.000000<y/>
<brkwall58/>
<ubrkwall42>
<x>6.000000<x/>
<y>22.000000<y/>
<ubrkwall42/>
<brkwall59>
<x>6.000000<x/>
<y>23.000000<y/>
<brkwall59/>
<ubrkwall43>
<x>6.000000<x/>
<y>24.000000<y/>
<ubrkwall43/>
<ubrkwall44>
<x>6.000000<x/>
<y>25.000000<y/>
<ubrkwall44/>
<ubrkwall45>
<x>6.000000<x/>
<y>26.000000<y/>
<ubrkwall45/>
<brkwall60>
<x>6.000000<x/>
<y>27.000000<y/>
<brkwall60/>
<floor60>
<x>6.000000<x/>
<y>28.000000<y/>
<floor60/>
<mapwall41>
<x>6.000000<x/>
<y>29.000000<y/>
<mapwall41/>
<mapwall42>
<x>7.000000<x/>
<y>0.000000<y/>
<mapwall42/>
<brkwall61>
<x>7.000000<x/>
<y>1.000000<y/>
<brkwall61/>
<ubrkwall46>
<x>7.000000<x/>
<y>2.000000<y/>
<ubrkwall46/>
<ubrkwall47>
<x>7.000000<x/>
<y>3.000000<y/>
<ubrkwall47/>
<floor61>
<x>7.000000<x/>
<y>4.000000<y/>
<floor61/>
<brkwall62>
<x>7.000000<x/>
<y>5.000000<y/>
<brkwall62/>
<ubrkwall48>
<x>7.000000<x/>
<y>6.000000<y/>
<ubrkwall48/>
<floor62>
<x>7.000000<x/>
<y>7.000000<y/>
<floor62/>
<floor63>
<x>7.000000<x/>
<y>8.000000<y/>
<floor63/>
<brkwall63>
<x>7.000000<x/>
<y>9.000000<y/>
<brkwall63/>
<floor64>
<x>7.000000<x/>
<y>10.000000<y/>
<floor64/>
<ubrkwall49>
<x>7.000000<x/>
<y>11.000000<y/>
<ubrkwall49/>
<brkwall64>
<x>7.000000<x/>
<y>12.000000<y/>
<brkwall64/>
<floor65>
<x>7.000000<x/>
<y>13.000000<y/>
<floor65/>
<floor66>
<x>7.000000<x/>
<y>14.000000<y/>
<floor66/>
<ubrkwall50>
<x>7.000000<x/>
<y>15.000000<y/>
<ubrkwall50/>
<brkwall65>
<x>7.000000<x/>
<y>16.000000<y/>
<brkwall65/>
<brkwall66>
<x>7.000000<x/>
<y>17.000000<y/>
<brkwall66/>
<brkwall67>
<x>7.000000<x/>
<y>18.000000<y/>
<brkwall67/>
<brkwall68>
<x>7.000000<x/>
<y>19.000000<y/>
<brkwall68/>
<brkwall69>
<x>7.000000<x/>
<y>20.000000<y/>
<brkwall69/>
<ubrkwall51>
<x>7.000000<x/>
<y>21.000000<y/>
<ubrkwall51/>
<brkwall70>
<x>7.000000<x/>
<y>22.000000<y/>
<brkwall70/>
<floor67>
<x>7.000000<x/>
<y>23.000000<y/>
<floor67/>
<floor68>
<x>7.000000<x/>
<y>24.000000<y/>
<floor68/>
<brkwall71>
<x>7.000000<x/>
<y>25.000000<y/>
<brkwall71/>
<brkwall72>
<x>7.000000<x/>
<y>26.000000<y/>
<brkwall72/>
<brkwall73>
<x>7.000000<x/>
<y>27.000000<y/>
<brkwall73/>
<brkwall74>
<x>7.000000<x/>
<y>28.000000<y/>
<brkwall74/>
<mapwall43>
<x>7.000000<x/>
<y>29.000000<y/>
<mapwall43/>
<mapwall44>
<x>8.000000<x/>
<y>0.000000<y/>
<mapwall44/>
<brkwall75>
<x>8.000000<x/>
<y>1.000000<y/>
<brkwall75/>
<ubrkwall52>
<x>8.000000<x/>
<y>2.000000<y/>
<ubrkwall52/>
<floor69>
<x>8.000000<x/>
<y>3.000000<y/>
<floor69/>
<brkwall76>
<x>8.000000<x/>
<y>4.000000<y/>
<brkwall76/>
<ubrkwall53>
<x>8.000000<x/>
<y>5.000000<y/>
<ubrkwall53/>
<brkwall77>
<x>8.000000<x/>
<y>6.000000<y/>
<brkwall77/>
<brkwall78>
<x>8.000000<x/>
<y>7.000000<y/>
<brkwall78/>
<floor70>
<x>8.000000<x/>
<y>8.000000<y/>
<floor70/>
<ubrkwall54>
<x>8.000000<x/>
<y>9.000000<y/>
<ubrkwall54/>
<ubrkwall55>
<x>8.000000<x/>
<y>10.000000<y/>
<ubrkwall55/>
<floor71>
<x>8.000000<x/>
<y>11.000000<y/>
<floor71/>
<ubrkwall56>
<x>8.000000<x/>
<y>12.000000<y/>
<ubrkwall56/>
<floor72>
<x>8.000000<x/>
<y>13.000000<y/>
<floor72/>
<brkwall79>
<x>8.000000<x/>
<y>14.000000<y/>
<brkwall79/>
<brkwall80>
<x>8.000000<x/>
<y>15.000000<y/>
<brkwall80/>
<brkwall81>
<x>8.000000<x/>
<y>16.000000<y/>
<brkwall81/>
<ubrkwall57>
<x>8.000000<x/>
<y>17.000000<y/>
<ubrkwall57/>
<brkwall82>
<x>8.000000<x/>
<y>18.000000<y/>
<brkwall82/>
<brkwall83>
<x>8.000000<x/>
<y>19.000000<y/>
<brkwall83/>
<ubrkwall58>
<x>8.000000<x/>
<y>20.000000<y/>
<ubrkwall58/>
<brkwall84>
<x>8.000000<x/>
<y>21.000000<y/>
<brkwall84/>
<ubrkwall59>
<x>8.000000<x/>
<y>22.000000<y/>
<ubrkwall59/>
<brkwall85>
<x>8.000000<x/>
<y>23.000000<y/>
<brkwall85/>
<brkwall86>
<x>8.000000<x/>
<y>24.000000<y/>
<brkwall86/>
<brkwall87>
<x>8.000000<x/>
<y>25.000000<y/>
<brkwall87/>
<floor73>
<x>8.000000<x/>
<y>26.000000<y/>
<floor73/>
<floor74>
<x>8.000000<x/>
<y>27.000000<y/>
<floor74/>
<brkwall88>
<x>8.000000<x/>
<y>28.000000<y/>
<brkwall88/>
<mapwall45>
<x>8.000000<x/>
<y>29.000000<y/>
<mapwall45/>
<mapwall46>
<x>9.000000<x/>
<y>0.000000<y/>
<mapwall46/>
<floor75>
<x>9.000000<x/>
<y>1.000000<y/>
<floor75/>
<brkwall89>
<x>9.000000<x/>
<y>2.000000<y/>
<brkwall89/>
<brkwall90>
<x>9.000000<x/>
<y>3.000000<y/>
<brkwall90/>
<ubrkwall60>
<x>9.000000<x/>
<y>4.000000<y/>
<ubrkwall60/>
<ubrkwall61>
<x>9.000000<x/>
<y>5.000000<y/>
<ubrkwall61/>
<ubrkwall62>
<x>9.000000<x/>
<y>6.000000<y/>
<ubrkwall62/>
<ubrkwall63>
<x>9.000000<x/>
<y>7.000000<y/>
<ubrkwall63/>
<floor76>
<x>9.000000<x/>
<y>8.000000<y/>
<floor76/>
<floor77>
<x>9.000000<x/>
<y>9.000000<y/>
<floor77/>
<brkwall91>
<x>9.000000<x/>
<y>10.000000<y/>
<brkwall91/>
<floor78>
<x>9.000000<x/>
<y>11.000000<y/>
<floor78/>
<floor79>
<x>9.000000<x/>
<y>12.000000<y/>
<floor79/>
<brkwall92>
<x>9.000000<x/>
<y>13.000000<y/>
<brkwall92/>
<brkwall93>
<x>9.000000<x/>
<y>14.000000<y/>
<brkwall93/>
<ubrkwall64>
<x>9.000000<x/>
<y>15.000000<y/>
<ubrkwall64/>
<ubrkwall65>
<x>9.000000<x/>
<y>16.000000<y/>
<ubrkwall65/>
<ubrkwall66>
<x>9.000000<x/>
<y>17.000000<y/>
<ubrkwall66/>
<ubrkwall67>
<x>9.000000<x/>
<y>18.000000<y/>
<ubrkwall67/>
<brkwall94>
<x>9.000000<x/>
<y>19.000000<y/>
<brkwall94/>
<floor80>
<x>9.000000<x/>
<y>20.000000<y/>
<floor80/>
<brkwall95>
<x>9.000000<x/>
<y>21.000000<y/>
<brkwall95/>
<floor81>
<x>9.000000<x/>
<y>22.000000<y/>
<floor81/>
<floor82>
<x>9.000000<x/>
<y>23.000000<y/>
<floor82/>
<brkwall96>
<x>9.000000<x/>
<y>24.000000<y/>
<brkwall96/>
<brkwall97>
<x>9.000000<x/>
<y>25.000000<y/>
<brkwall97/>
<brkwall98>
<x>9.000000<x/>
<y>26.000000<y/>
<brkwall98/>
<ubrkwall68>
<x>9.000000<x/>
<y>27.000000<y/>
<ubrkwall68/>
<brkwall99>
<x>9.000000<x/>
<y>28.000000<y/>
<brkwall99/>
<mapwall47>
<x>9.000000<x/>
<y>29.000000<y/>
<mapwall47/>
<mapwall48>
<x>10.000000<x/>
<y>0.000000<y/>
<mapwall48/>
<brkwall100>
<x>10.000000<x/>
<y>1.000000<y/>
<brkwall100/>
<floor83>
<x>10.000000<x/>
<y>2.000000<y/>
<floor83/>
<floor84>
<x>10.000000<x/>
<y>3.000000<y/>
<floor84/>
<brkwall101>
<x>10.000000<x/>
<y>4.000000<y/>
<brkwall101/>
<floor85>
<x>10.000000<x/>
<y>5.000000<y/>
<floor85/>
<ubrkwall69>
<x>10.000000<x/>
<y>6.000000<y/>
<ubrkwall69/>
<floor86>
<x>10.000000<x/>
<y>7.000000<y/>
<floor86/>
<ubrkwall70>
<x>10.000000<x/>
<y>8.000000<y/>
<ubrkwall70/>
<ubrkwall71>
<x>10.000000<x/>
<y>9.000000<y/>
<ubrkwall71/>
<brkwall102>
<x>10.000000<x/>
<y>10.000000<y/>
<brkwall102/>
<floor87>
<x>10.000000<x/>
<y>11.000000<y/>
<floor87/>
<brkwall103>
<x>10.000000<x/>
<y>12.000000<y/>
<brkwall103/>
<floor88>
<x>10.000000<x/>
<y>13.000000<y/>
<floor88/>
<ubrkwall72>
<x>10.000000<x/>
<y>14.000000<y/>
<ubrkwall72/>
<floor89>
<x>10.000000<x/>
<y>15.000000<y/>
<floor89/>
<floor90>
<x>10.000000<x/>
<y>16.000000<y/>
<floor90/>
<brkwall104>
<x>10.000000<x/>
<y>17.000000<y/>
<brkwall104/>
<floor91>
<x>10.000000<x/>
<y>18.000000<y/>
<floor91/>
<brkwall105>
<x>10.000000<x/>
<y>19.000000<y/>
<brkwall105/>
<floor92>
<x>10.000000<x/>
<y>20.000000<y/>
<floor92/>
<floor93>
<x>10.000000<x/>
<y>21.000000<y/>
<floor93/>
<ubrkwall73>
<x>10.000000<x/>
<y>22.000000<y/>
<ubrkwall73/>
<brkwall106>
<x>10.000000<x/>
<y>23.000000<y/>
<brkwall106/>
<floor94>
<x>10.000000<x/>
<y>24.000000<y/>
<floor94/>
<floor95>
<x>10.000000<x/>
<y>25.000000<y/>
<floor95/>
<ubrkwall74>
<x>10.000000<x/>
<y>26.000000<y/>
<ubrkwall74/>
<ubrkwall75>
<x>10.000000<x/>
<y>27.000000<y/>
<ubrkwall75/>
<floor96>
<x>10.000000<x/>
<y>28.000000<y/>
<floor96/>
<mapwall49>
<x>10.000000<x/>
<y>29.000000<y/>
<mapwall49/>
<mapwall50>
<x>11.000000<x/>
<y>0.000000<y/>
<mapwall50/>
<brkwall107>
<x>11.000000<x/>
<y>1.000000<y/>
<brkwall107/>
<brkwall108>
<x>11.000000<x/>
<y>2.000000<y/>
<brkwall108/>
<floor97>
<x>11.000000<x/>
<y>3.000000<y/>
<floor97/>
<ubrkwall76>
<x>11.000000<x/>
<y>4.000000<y/>
<ubrkwall76/>
<brkwall109>
<x>11.000000<x/>
<y>5.000000<y/>
<brkwall109/>
<ubrkwall77>
<x>11.000000<x/>
<y>6.000000<y/>
<ubrkwall77/>
<floor98>
<x>11.000000<x/>
<y>7.000000<y/>
<floor98/>
<floor99>
<x>11.000000<x/>
<y>8.000000<y/>
<floor99/>
<ubrkwall78>
<x>11.000000<x/>
<y>9.000000<y/>
<ubrkwall78/>
<brkwall110>
<x>11.000000<x/>
<y>10.000000<y/>
<brkwall110/>
<ubrkwall79>
<x>11.000000<x/>
<y>11.000000<y/>
<ubrkwall79/>
<floor100>
<x>11.000000<x/>
<y>12.000000<y/>
<floor100/>
<ubrkwall80>
<x>11.000000<x/>
<y>13.000000<y/>
<ubrkwall80/>
<ubrkwall81>
<x>11.000000<x/>
<y>14.000000<y/>
<ubrkwall81/>
<floor101>
<x>11.000000<x/>
<y>15.000000<y/>
<floor101/>
<ubrkwall82>
<x>11.000000<x/>
<y>16.000000<y/>
<ubrkwall82/>
<ubrkwall83>
<x>11.000000<x/>
<y>17.000000<y/>
<ubrkwall83/>
<ubrkwall84>
<x>11.000000<x/>
<y>18.000000<y/>
<ubrkwall84/>
<brkwall111>
<x>11.000000<x/>
<y>19.000000<y/>
<brkwall111/>
<floor102>
<x>11.000000<x/>
<y>20.000000<y/>
<floor102/>
<brkwall112>
<x>11.000000<x/>
<y>21.000000<y/>
<brkwall112/>
<ubrkwall85>
<x>11.000000<x/>
<y>22.000000<y/>
<ubrkwall85/>
<brkwall113>
<x>11.000000<x/>
<y>23.000000<y/>
<brkwall113/>
<floor103>
<x>11.000000<x/>
<y>24.000000<y/>
<floor103/>
<ubrkwall86>
<x>11.000000<x/>
<y>25.000000<y/>
<ubrkwall86/>
<brkwall114>
<x>11.000000<x/>
<y>26.000000<y/>
<brkwall114/>
<floor104>
<x>11.000000<x/>
<y>27.000000<y/>
<floor104/>
<brkwall115>
<x>11.000000<x/>
<y>28.000000<y/>
<brkwall115/>
<mapwall51>
<x>11.000000<x/>
<y>29.000000<y/>
<mapwall51/>
<mapwall52>
<x>12.000000<x/>
<y>0.000000<y/>
<mapwall52/>
<brkwall116>
<x>12.000000<x/>
<y>1.000000<y/>
<brkwall116/>
<floor105>
<x>12.000000<x/>
<y>2.000000<y/>
<floor105/>
<ubrkwall87>
<x>12.000000<x/>
<y>3.000000<y/>
<ubrkwall87/>
<ubrkwall88>
<x>12.000000<x/>
<y>4.000000<y/>
<ubrkwall88/>
<ubrkwall89>
<x>12.000000<x/>
<y>5.000000<y/>
<ubrkwall89/>
<brkwall117>
<x>12.000000<x/>
<y>6.000000<y/>
<brkwall117/>
<brkwall118>
<x>12.000000<x/>
<y>7.000000<y/>
<brkwall118/>
<brkwall119>
<x>12.000000<x/>
<y>8.000000<y/>
<brkwall119/>
<brkwall120>
<x>12.000000<x/>
<y>9.000000<y/>
<brkwall120/>
<floor106>
<x>12.000000<x/>
<y>10.000000<y/>
<floor106/>
<brkwall121>
<x>12.000000<x/>
<y>11.000000<y/>
<brkwall121/>
<ubrkwall90>
<x>12.000000<x/>
<y>12.000000<y/>
<ubrkwall90/>
<ubrkwall91>
<x>12.000000<x/>
<y>13.000000<y/>
<ubrkwall91/>
<floor107>
<x>12.000000<x/>
<y>14.000000<y/>
<floor107/>
<brkwall122>
<x>12.000000<x/>
<y>15.000000<y/>
<brkwall122/>
<floor108>
<x>12.000000<x/>
<y>16.000000<y/>
<floor108/>
<brkwall123>
<x>12.000000<x/>
<y>17.000000<y/>
<brkwall123/>
<ubrkwall92>
<x>12.000000<x/>
<y>18.000000<y/>
<ubrkwall92/>
<brkwall124>
<x>12.000000<x/>
<y>19.000000<y/>
<brkwall124/>
<ubrkwall93>
<x>12.000000<x/>
<y>20.000000<y/>
<ubrkwall93/>
<brkwall125>
<x>12.000000<x/>
<y>21.000000<y/>
<brkwall125/>
<ubrkwall94>
<x>12.000000<x/>
<y>22.000000<y/>
<ubrkwall94/>
<floor109>
<x>12.000000<x/>
<y>23.000000<y/>
<floor109/>
<ubrkwall95>
<x>12.000000<x/>
<y>24.000000<y/>
<ubrkwall95/>
<brkwall126>
<x>12.000000<x/>
<y>25.000000<y/>
<brkwall126/>
<brkwall127>
<x>12.000000<x/>
<y>26.000000<y/>
<brkwall127/>
<floor110>
<x>12.000000<x/>
<y>27.000000<y/>
<floor110/>
<brkwall128>
<x>12.000000<x/>
<y>28.000000<y/>
<brkwall128/>
<mapwall53>
<x>12.000000<x/>
<y>29.000000<y/>
<mapwall53/>
<mapwall54>
<x>13.000000<x/>
<y>0.000000<y/>
<mapwall54/>
<brkwall129>
<x>13.000000<x/>
<y>1.000000<y/>
<brkwall129/>
<floor111>
<x>13.000000<x/>
<y>2.000000<y/>
<floor111/>
<brkwall130>
<x>13.000000<x/>
<y>3.000000<y/>
<brkwall130/>
<floor112>
<x>13.000000<x/>
<y>4.000000<y/>
<floor112/>
<floor113>
<x>13.000000<x/>
<y>5.000000<y/>
<floor113/>
<brkwall131>
<x>13.000000<x/>
<y>6.000000<y/>
<brkwall131/>
<brkwall132>
<x>13.000000<x/>
<y>7.000000<y/>
<brkwall132/>
<floor114>
<x>13.000000<x/>
<y>8.000000<y/>
<floor114/>
<floor115>
<x>13.000000<x/>
<y>9.000000<y/>
<floor115/>
<floor116>
<x>13.000000<x/>
<y>10.000000<y/>
<floor116/>
<brkwall133>
<x>13.000000<x/>
<y>11.000000<y/>
<brkwall133/>
<floor117>
<x>13.000000<x/>
<y>12.000000<y/>
<floor117/>
<floor118>
<x>13.000000<x/>
<y>13.000000<y/>
<floor118/>
<ubrkwall96>
<x>13.000000<x/>
<y>14.000000<y/>
<ubrkwall96/>
<brkwall134>
<x>13.000000<x/>
<y>15.000000<y/>
<brkwall134/>
<ubrkwall97>
<x>13.000000<x/>
<y>16.000000<y/>
<ubrkwall97/>
<brkwall135>
<x>13.000000<x/>
<y>17.000000<y/>
<brkwall135/>
<brkwall136>
<x>13.000000<x/>
<y>18.000000<y/>
<brkwall136/>
<floor119>
<x>13.000000<x/>
<y>19.000000<y/>
<floor119/>
<brkwall137>
<x>13.000000<x/>
<y>20.000000<y/>
<brkwall137/>
<floor120>
<x>13.000000<x/>
<y>21.000000<y/>
<floor120/>
<brkwall138>
<x>13.000000<x/>
<y>22.000000<y/>
<brkwall138/>
<floor121>
<x>13.000000<x/>
<y>23.000000<y/>
<floor121/>
<brkwall139>
<x>13.000000<x/>
<y>24.000000<y/>
<brkwall139/>
<floor122>
<x>13.000000<x/>
<y>25.000000<y/>
<floor122/>
<floor123>
<x>13.000000<x/>
<y>26.000000<y/>
<floor123/>
<brkwall140>
<x>13.000000<x/>
<y>27.000000<y/>
<brkwall140/>
<brkwall141>
<x>13.000000<x/>
<y>28.000000<y/>
<brkwall141/>
<mapwall55>
<x>13.000000<x/>
<y>29.000000<y/>
<mapwall55/>
<mapwall56>
<x>14.000000<x/>
<y>0.000000<y/>
<mapwall56/>
<floor124>
<x>14.000000<x/>
<y>1.000000<y/>
<floor124/>
<floor125>
<x>14.000000<x/>
<y>2.000000<y/>
<floor125/>
<brkwall142>
<x>14.000000<x/>
<y>3.000000<y/>
<brkwall142/>
<brkwall143>
<x>14.000000<x/>
<y>4.000000<y/>
<brkwall143/>
<ubrkwall98>
<x>14.000000<x/>
<y>5.000000<y/>
<ubrkwall98/>
<ubrkwall99>
<x>14.000000<x/>
<y>6.000000<y/>
<ubrkwall99/>
<ubrkwall100>
<x>14.000000<x/>
<y>7.000000<y/>
<ubrkwall100/>
<ubrkwall101>
<x>14.000000<x/>
<y>8.000000<y/>
<ubrkwall101/>
<floor126>
<x>14.000000<x/>
<y>9.000000<y/>
<floor126/>
<brkwall144>
<x>14.000000<x/>
<y>10.000000<y/>
<brkwall144/>
<ubrkwall102>
<x>14.000000<x/>
<y>11.000000<y/>
<ubrkwall102/>
<ubrkwall103>
<x>14.000000<x/>
<y>12.000000<y/>
<ubrkwall103/>
<ubrkwall104>
<x>14.000000<x/>
<y>13.000000<y/>
<ubrkwall104/>
<ubrkwall105>
<x>14.000000<x/>
<y>14.000000<y/>
<ubrkwall105/>
<ubrkwall106>
<x>14.000000<x/>
<y>15.000000<y/>
<ubrkwall106/>
<floor127>
<x>14.000000<x/>
<y>16.000000<y/>
<floor127/>
<ubrkwall107>
<x>14.000000<x/>
<y>17.000000<y/>
<ubrkwall107/>
<brkwall145>
<x>14.000000<x/>
<y>18.000000<y/>
<brkwall145/>
<floor128>
<x>14.000000<x/>
<y>19.000000<y/>
<floor128/>
<brkwall146>
<x>14.000000<x/>
<y>20.000000<y/>
<brkwall146/>
<floor129>
<x>14.000000<x/>
<y>21.000000<y/>
<floor129/>
<floor130>
<x>14.000000<x/>
<y>22.000000<y/>
<floor130/>
<floor131>
<x>14.000000<x/>
<y>23.000000<y/>
<floor131/>
<floor132>
<x>14.000000<x/>
<y>24.000000<y/>
<floor132/>
<floor133>
<x>14.000000<x/>
<y>25.000000<y/>
<floor133/>
<brkwall147>
<x>14.000000<x/>
<y>26.000000<y/>
<brkwall147/>
<floor134>
<x>14.000000<x/>
<y>27.000000<y/>
<floor134/>
<brkwall148>
<x>14.000000<x/>
<y>28.000000<y/>
<brkwall148/>
<mapwall57>
<x>14.000000<x/>
<y>29.000000<y/>
<mapwall57/>
<mapwall58>
<x>15.000000<x/>
<y>0.000000<y/>
<mapwall58/>
<floor135>
<x>15.000000<x/>
<y>1.000000<y/>
<floor135/>
<brkwall149>
<x>15.000000<x/>
<y>2.000000<y/>
<brkwall149/>
<floor136>
<x>15.000000<x/>
<y>3.000000<y/>
<floor136/>
<floor137>
<x>15.000000<x/>
<y>4.000000<y/>
<floor137/>
<floor138>
<x>15.000000<x/>
<y>5.000000<y/>
<floor138/>
<floor139>
<x>15.000000<x/>
<y>6.000000<y/>
<floor139/>
<floor140>
<x>15.000000<x/>
<y>7.000000<y/>
<floor140/>
<floor141>
<x>15.000000<x/>
<y>8.000000<y/>
<floor141/>
<floor142>
<x>15.000000<x/>
<y>9.000000<y/>
<floor142/>
<brkwall150>
<x>15.000000<x/>
<y>10.000000<y/>
<brkwall150/>
<floor143>
<x>15.000000<x/>
<y>11.000000<y/>
<floor143/>
<ubrkwall108>
<x>15.000000<x/>
<y>12.000000<y/>
<ubrkwall108/>
<brkwall151>
<x>15.000000<x/>
<y>13.000000<y/>
<brkwall151/>
<floor144>
<x>15.000000<x/>
<y>14.000000<y/>
<floor144/>
<brkwall152>
<x>15.000000<x/>
<y>15.000000<y/>
<brkwall152/>
<floor145>
<x>15.000000<x/>
<y>16.000000<y/>
<floor145/>
<brkwall153>
<x>15.000000<x/>
<y>17.000000<y/>
<brkwall153/>
<brkwall154>
<x>15.000000<x/>
<y>18.000000<y/>
<brkwall154/>
<ubrkwall109>
<x>15.000000<x/>
<y>19.000000<y/>
<ubrkwall109/>
<ubrkwall110>
<x>15.000000<x/>
<y>20.000000<y/>
<ubrkwall110/>
<floor146>
<x>15.000000<x/>
<y>21.000000<y/>
<floor146/>
<floor147>
<x>15.000000<x/>
<y>22.000000<y/>
<floor147/>
<floor148>
<x>15.000000<x/>
<y>23.000000<y/>
<floor148/>
<ubrkwall111>
<x>15.000000<x/>
<y>24.000000<y/>
<ubrkwall111/>
<ubrkwall112>
<x>15.000000<x/>
<y>25.000000<y/>
<ubrkwall112/>
<ubrkwall113>
<x>15.000000<x/>
<y>26.000000<y/>
<ubrkwall113/>
<brkwall155>
<x>15.000000<x/>
<y>27.000000<y/>
<brkwall155/>
<floor149>
<x>15.000000<x/>
<y>28.000000<y/>
<floor149/>
<mapwall59>
<x>15.000000<x/>
<y>29.000000<y/>
<mapwall59/>
<mapwall60>
<x>16.000000<x/>
<y>0.000000<y/>
<mapwall60/>
<brkwall156>
<x>16.000000<x/>
<y>1.000000<y/>
<brkwall156/>
<floor150>
<x>16.000000<x/>
<y>2.000000<y/>
<floor150/>
<ubrkwall114>
<x>16.000000<x/>
<y>3.000000<y/>
<ubrkwall114/>
<brkwall157>
<x>16.000000<x/>
<y>4.000000<y/>
<brkwall157/>
<brkwall158>
<x>16.000000<x/>
<y>5.000000<y/>
<brkwall158/>
<brkwall159>
<x>16.000000<x/>
<y>6.000000<y/>
<brkwall159/>
<brkwall160>
<x>16.000000<x/>
<y>7.000000<y/>
<brkwall160/>
<brkwall161>
<x>16.000000<x/>
<y>8.000000<y/>
<brkwall161/>
<floor151>
<x>16.000000<x/>
<y>9.000000<y/>
<floor151/>
<floor152>
<x>16.000000<x/>
<y>10.000000<y/>
<floor152/>
<ubrkwall115>
<x>16.000000<x/>
<y>11.000000<y/>
<ubrkwall115/>
<floor153>
<x>16.000000<x/>
<y>12.000000<y/>
<floor153/>
<ubrkwall116>
<x>16.000000<x/>
<y>13.000000<y/>
<ubrkwall116/>
<floor154>
<x>16.000000<x/>
<y>14.000000<y/>
<floor154/>
<ubrkwall117>
<x>16.000000<x/>
<y>15.000000<y/>
<ubrkwall117/>
<floor155>
<x>16.000000<x/>
<y>16.000000<y/>
<floor155/>
<ubrkwall118>
<x>16.000000<x/>
<y>17.000000<y/>
<ubrkwall118/>
<floor156>
<x>16.000000<x/>
<y>18.000000<y/>
<floor156/>
<ubrkwall119>
<x>16.000000<x/>
<y>19.000000<y/>
<ubrkwall119/>
<brkwall162>
<x>16.000000<x/>
<y>20.000000<y/>
<brkwall162/>
<floor157>
<x>16.000000<x/>
<y>21.000000<y/>
<floor157/>
<floor158>
<x>16.000000<x/>
<y>22.000000<y/>
<floor158/>
<floor159>
<x>16.000000<x/>
<y>23.000000<y/>
<floor159/>
<brkwall163>
<x>16.000000<x/>
<y>24.000000<y/>
<brkwall163/>
<ubrkwall120>
<x>16.000000<x/>
<y>25.000000<y/>
<ubrkwall120/>
<ubrkwall121>
<x>16.000000<x/>
<y>26.000000<y/>
<ubrkwall121/>
<floor160>
<x>16.000000<x/>
<y>27.000000<y/>
<floor160/>
<floor161>
<x>16.000000<x/>
<y>28.000000<y/>
<floor161/>
<mapwall61>
<x>16.000000<x/>
<y>29.000000<y/>
<mapwall61/>
<mapwall62>
<x>17.000000<x/>
<y>0.000000<y/>
<mapwall62/>
<floor162>
<x>17.000000<x/>
<y>1.000000<y/>
<floor162/>
<floor163>
<x>17.000000<x/>
<y>2.000000<y/>
<floor163/>
<brkwall164>
<x>17.000000<x/>
<y>3.000000<y/>
<brkwall164/>
<floor164>
<x>17.000000<x/>
<y>4.000000<y/>
<floor164/>
<floor165>
<x>17.000000<x/>
<y>5.000000<y/>
<floor165/>
<brkwall165>
<x>17.000000<x/>
<y>6.000000<y/>
<brkwall165/>
<floor166>
<x>17.000000<x/>
<y>7.000000<y/>
<floor166/>
<floor167>
<x>17.000000<x/>
<y>8.000000<y/>
<floor167/>
<ubrkwall122>
<x>17.000000<x/>
<y>9.000000<y/>
<ubrkwall122/>
<ubrkwall123>
<x>17.000000<x/>
<y>10.000000<y/>
<ubrkwall123/>
<floor168>
<x>17.000000<x/>
<y>11.000000<y/>
<floor168/>
<brkwall166>
<x>17.000000<x/>
<y>12.000000<y/>
<brkwall166/>
<floor169>
<x>17.000000<x/>
<y>13.000000<y/>
<floor169/>
<ubrkwall124>
<x>17.000000<x/>
<y>14.000000<y/>
<ubrkwall124/>
<floor170>
<x>17.000000<x/>
<y>15.000000<y/>
<floor170/>
<ubrkwall125>
<x>17.000000<x/>
<y>16.000000<y/>
<ubrkwall125/>
<ubrkwall126>
<x>17.000000<x/>
<y>17.000000<y/>
<ubrkwall126/>
<brkwall167>
<x>17.000000<x/>
<y>18.000000<y/>
<brkwall167/>
<floor171>
<x>17.000000<x/>
<y>19.000000<y/>
<floor171/>
<brkwall168>
<x>17.000000<x/>
<y>20.000000<y/>
<brkwall168/>
<brkwall169>
<x>17.000000<x/>
<y>21.000000<y/>
<brkwall169/>
<ubrkwall127>
<x>17.000000<x/>
<y>22.000000<y/>
<ubrkwall127/>
<floor172>
<x>17.000000<x/>
<y>23.000000<y/>
<floor172/>
<brkwall170>
<x>17.000000<x/>
<y>24.000000<y/>
<brkwall170/>
<ubrkwall128>
<x>17.000000<x/>
<y>25.000000<y/>
<ubrkwall128/>
<floor173>
<x>17.000000<x/>
<y>26.000000<y/>
<floor173/>
<floor174>
<x>17.000000<x/>
<y>27.000000<y/>
<floor174/>
<floor175>
<x>17.000000<x/>
<y>28.000000<y/>
<floor175/>
<mapwall63>
<x>17.000000<x/>
<y>29.000000<y/>
<mapwall63/>
<mapwall64>
<x>18.000000<x/>
<y>0.000000<y/>
<mapwall64/>
<brkwall171>
<x>18.000000<x/>
<y>1.000000<y/>
<brkwall171/>
<ubrkwall129>
<x>18.000000<x/>
<y>2.000000<y/>
<ubrkwall129/>
<floor176>
<x>18.000000<x/>
<y>3.000000<y/>
<floor176/>
<ubrkwall130>
<x>18.000000<x/>
<y>4.000000<y/>
<ubrkwall130/>
<brkwall172>
<x>18.000000<x/>
<y>5.000000<y/>
<brkwall172/>
<floor177>
<x>18.000000<x/>
<y>6.000000<y/>
<floor177/>
<ubrkwall131>
<x>18.000000<x/>
<y>7.000000<y/>
<ubrkwall131/>
<floor178>
<x>18.000000<x/>
<y>8.000000<y/>
<floor178/>
<brkwall173>
<x>18.000000<x/>
<y>9.000000<y/>
<brkwall173/>
<floor179>
<x>18.000000<x/>
<y>10.000000<y/>
<floor179/>
<ubrkwall132>
<x>18.000000<x/>
<y>11.000000<y/>
<ubrkwall132/>
<ubrkwall133>
<x>18.000000<x/>
<y>12.000000<y/>
<ubrkwall133/>
<floor180>
<x>18.000000<x/>
<y>13.000000<y/>
<floor180/>
<floor181>
<x>18.000000<x/>
<y>14.000000<y/>
<floor181/>
<brkwall174>
<x>18.000000<x/>
<y>15.000000<y/>
<brkwall174/>
<brkwall175>
<x>18.000000<x/>
<y>16.000000<y/>
<brkwall175/>
<brkwall176>
<x>18.000000<x/>
<y>17.000000<y/>
<brkwall176/>
<brkwall177>
<x>18.000000<x/>
<y>18.000000<y/>
<brkwall177/>
<brkwall178>
<x>18.000000<x/>
<y>19.000000<y/>
<brkwall178/>
<ubrkwall134>
<x>18.000000<x/>
<y>20.000000<y/>
<ubrkwall134/>
<brkwall179>
<x>18.000000<x/>
<y>21.000000<y/>
<brkwall179/>
<brkwall180>
<x>18.000000<x/>
<y>22.000000<y/>
<brkwall180/>
<ubrkwall135>
<x>18.000000<x/>
<y>23.000000<y/>
<ubrkwall135/>
<ubrkwall136>
<x>18.000000<x/>
<y>24.000000<y/>
<ubrkwall136/>
<floor182>
<x>18.000000<x/>
<y>25.000000<y/>
<floor182/>
<brkwall181>
<x>18.000000<x/>
<y>26.000000<y/>
<brkwall181/>
<ubrkwall137>
<x>18.000000<x/>
<y>27.000000<y/>
<ubrkwall137/>
<floor183>
<x>18.000000<x/>
<y>28.000000<y/>
<floor183/>
<mapwall65>
<x>18.000000<x/>
<y>29.000000<y/>
<mapwall65/>
<mapwall66>
<x>19.000000<x/>
<y>0.000000<y/>
<mapwall66/>
<brkwall182>
<x>19.000000<x/>
<y>1.000000<y/>
<brkwall182/>
<ubrkwall138>
<x>19.000000<x/>
<y>2.000000<y/>
<ubrkwall138/>
<brkwall183>
<x>19.000000<x/>
<y>3.000000<y/>
<brkwall183/>
<brkwall184>
<x>19.000000<x/>
<y>4.000000<y/>
<brkwall184/>
<brkwall185>
<x>19.000000<x/>
<y>5.000000<y/>
<brkwall185/>
<ubrkwall139>
<x>19.000000<x/>
<y>6.000000<y/>
<ubrkwall139/>
<ubrkwall140>
<x>19.000000<x/>
<y>7.000000<y/>
<ubrkwall140/>
<floor184>
<x>19.000000<x/>
<y>8.000000<y/>
<floor184/>
<brkwall186>
<x>19.000000<x/>
<y>9.000000<y/>
<brkwall186/>
<ubrkwall141>
<x>19.000000<x/>
<y>10.000000<y/>
<ubrkwall141/>
<floor185>
<x>19.000000<x/>
<y>11.000000<y/>
<floor185/>
<floor186>
<x>19.000000<x/>
<y>12.000000<y/>
<floor186/>
<ubrkwall142>
<x>19.000000<x/>
<y>13.000000<y/>
<ubrkwall142/>
<brkwall187>
<x>19.000000<x/>
<y>14.000000<y/>
<brkwall187/>
<ubrkwall143>
<x>19.000000<x/>
<y>15.000000<y/>
<ubrkwall143/>
<brkwall188>
<x>19.000000<x/>
<y>16.000000<y/>
<brkwall188/>
<brkwall189>
<x>19.000000<x/>
<y>17.000000<y/>
<brkwall189/>
<ubrkwall144>
<x>19.000000<x/>
<y>18.000000<y/>
<ubrkwall144/>
<brkwall190>
<x>19.000000<x/>
<y>19.000000<y/>
<brkwall190/>
<ubrkwall145>
<x>19.000000<x/>
<y>20.000000<y/>
<ubrkwall145/>
<ubrkwall146>
<x>19.000000<x/>
<y>21.000000<y/>
<ubrkwall146/>
<ubrkwall147>
<x>19.000000<x/>
<y>22.000000<y/>
<ubrkwall147/>
<brkwall191>
<x>19.000000<x/>
<y>23.000000<y/>
<brkwall191/>
<brkwall192>
<x>19.000000<x/>
<y>24.000000<y/>
<brkwall192/>
<brkwall193>
<x>19.000000<x/>
<y>25.000000<y/>
<brkwall193/>
<floor187>
<x>19.000000<x/>
<y>26.000000<y/>
<floor187/>
<ubrkwall148>
<x>19.000000<x/>
<y>27.000000<y/>
<ubrkwall148/>
<brkwall194>
<x>19.000000<x/>
<y>28.000000<y/>
<brkwall194/>
<mapwall67>
<x>19.000000<x/>
<y>29.000000<y/>
<mapwall67/>
<mapwall68>
<x>20.000000<x/>
<y>0.000000<y/>
<mapwall68/>
<brkwall195>
<x>20.000000<x/>
<y>1.000000<y/>
<brkwall195/>
<brkwall196>
<x>20.000000<x/>
<y>2.000000<y/>
<brkwall196/>
<brkwall197>
<x>20.000000<x/>
<y>3.000000<y/>
<brkwall197/>
<ubrkwall149>
<x>20.000000<x/>
<y>4.000000<y/>
<ubrkwall149/>
<brkwall198>
<x>20.000000<x/>
<y>5.000000<y/>
<brkwall198/>
<ubrkwall150>
<x>20.000000<x/>
<y>6.000000<y/>
<ubrkwall150/>
<floor188>
<x>20.000000<x/>
<y>7.000000<y/>
<floor188/>
<ubrkwall151>
<x>20.000000<x/>
<y>8.000000<y/>
<ubrkwall151/>
<floor189>
<x>20.000000<x/>
<y>9.000000<y/>
<floor189/>
<floor190>
<x>20.000000<x/>
<y>10.000000<y/>
<floor190/>
<floor191>
<x>20.000000<x/>
<y>11.000000<y/>
<floor191/>
<ubrkwall152>
<x>20.000000<x/>
<y>12.000000<y/>
<ubrkwall152/>
<brkwall199>
<x>20.000000<x/>
<y>13.000000<y/>
<brkwall199/>
<ubrkwall153>
<x>20.000000<x/>
<y>14.000000<y/>
<ubrkwall153/>
<ubrkwall154>
<x>20.000000<x/>
<y>15.000000<y/>
<ubrkwall154/>
<ubrkwall155>
<x>20.000000<x/>
<y>16.000000<y/>
<ubrkwall155/>
<brkwall200>
<x>20.000000<x/>
<y>17.000000<y/>
<brkwall200/>
<ubrkwall156>
<x>20.000000<x/>
<y>18.000000<y/>
<ubrkwall156/>
<ubrkwall157>
<x>20.000000<x/>
<y>19.000000<y/>
<ubrkwall157/>
<ubrkwall158>
<x>20.000000<x/>
<y>20.000000<y/>
<ubrkwall158/>
<brkwall201>
<x>20.000000<x/>
<y>21.000000<y/>
<brkwall201/>
<brkwall202>
<x>20.000000<x/>
<y>22.000000<y/>
<brkwall202/>
<floor192>
<x>20.000000<x/>
<y>23.000000<y/>
<floor192/>
<floor193>
<x>20.000000<x/>
<y>24.000000<y/>
<floor193/>
<floor194>
<x>20.000000<x/>
<y>25.000000<y/>
<floor194/>
<ubrkwall159>
<x>20.000000<x/>
<y>26.000000<y/>
<ubrkwall159/>
<floor195>
<x>20.000000<x/>
<y>27.000000<y/>
<floor195/>
<brkwall203>
<x>20.000000<x/>
<y>28.000000<y/>
<brkwall203/>
<mapwall69>
<x>20.000000<x/>
<y>29.000000<y/>
<mapwall69/>
<mapwall70>
<x>21.000000<x/>
<y>0.000000<y/>
<mapwall70/>
<floor196>
<x>21.000000<x/>
<y>1.000000<y/>
<floor196/>
<brkwall204>
<x>21.000000<x/>
<y>2.000000<y/>
<brkwall204/>
<ubrkwall160>
<x>21.000000<x/>
<y>3.000000<y/>
<ubrkwall160/>
<brkwall205>
<x>21.000000<x/>
<y>4.000000<y/>
<brkwall205/>
<floor197>
<x>21.000000<x/>
<y>5.000000<y/>
<floor197/>
<ubrkwall161>
<x>21.000000<x/>
<y>6.000000<y/>
<ubrkwall161/>
<ubrkwall162>
<x>21.000000<x/>
<y>7.000000<y/>
<ubrkwall162/>
<brkwall206>
<x>21.000000<x/>
<y>8.000000<y/>
<brkwall206/>
<brkwall207>
<x>21.000000<x/>
<y>9.000000<y/>
<brkwall207/>
<floor198>
<x>21.000000<x/>
<y>10.000000<y/>
<floor198/>
<floor199>
<x>21.000000<x/>
<y>11.000000<y/>
<floor199/>
<ubrkwall163>
<x>21.000000<x/>
<y>12.000000<y/>
<ubrkwall163/>
<ubrkwall164>
<x>21.000000<x/>
<y>13.000000<y/>
<ubrkwall164/>
<ubrkwall165>
<x>21.000000<x/>
<y>14.000000<y/>
<ubrkwall165/>
<floor200>
<x>21.000000<x/>
<y>15.000000<y/>
<floor200/>
<brkwall208>
<x>21.000000<x/>
<y>16.000000<y/>
<brkwall208/>
<brkwall209>
<x>21.000000<x/>
<y>17.000000<y/>
<brkwall209/>
<floor201>
<x>21.000000<x/>
<y>18.000000<y/>
<floor201/>
<floor202>
<x>21.000000<x/>
<y>19.000000<y/>
<floor202/>
<ubrkwall166>
<x>21.000000<x/>
<y>20.000000<y/>
<ubrkwall166/>
<brkwall210>
<x>21.000000<x/>
<y>21.000000<y/>
<brkwall210/>
<ubrkwall167>
<x>21.000000<x/>
<y>22.000000<y/>
<ubrkwall167/>
<brkwall211>
<x>21.000000<x/>
<y>23.000000<y/>
<brkwall211/>
<ubrkwall168>
<x>21.000000<x/>
<y>24.000000<y/>
<ubrkwall168/>
<floor203>
<x>21.000000<x/>
<y>25.000000<y/>
<floor203/>
<ubrkwall169>
<x>21.000000<x/>
<y>26.000000<y/>
<ubrkwall169/>
<brkwall212>
<x>21.000000<x/>
<y>27.000000<y/>
<brkwall212/>
<brkwall213>
<x>21.000000<x/>
<y>28.000000<y/>
<brkwall213/>
<mapwall71>
<x>21.000000<x/>
<y>29.000000<y/>
<mapwall71/>
<mapwall72>
<x>22.000000<x/>
<y>0.000000<y/>
<mapwall72/>
<floor204>
<x>22.000000<x/>
<y>1.000000<y/>
<floor204/>
<ubrkwall170>
<x>22.000000<x/>
<y>2.000000<y/>
<ubrkwall170/>
<floor205>
<x>22.000000<x/>
<y>3.000000<y/>
<floor205/>
<floor206>
<x>22.000000<x/>
<y>4.000000<y/>
<floor206/>
<ubrkwall171>
<x>22.000000<x/>
<y>5.000000<y/>
<ubrkwall171/>
<floor207>
<x>22.000000<x/>
<y>6.000000<y/>
<floor207/>
<brkwall214>
<x>22.000000<x/>
<y>7.000000<y/>
<brkwall214/>
<floor208>
<x>22.000000<x/>
<y>8.000000<y/>
<floor208/>
<ubrkwall172>
<x>22.000000<x/>
<y>9.000000<y/>
<ubrkwall172/>
<brkwall215>
<x>22.000000<x/>
<y>10.000000<y/>
<brkwall215/>
<brkwall216>
<x>22.000000<x/>
<y>11.000000<y/>
<brkwall216/>
<brkwall217>
<x>22.000000<x/>
<y>12.000000<y/>
<brkwall217/>
<ubrkwall173>
<x>22.000000<x/>
<y>13.000000<y/>
<ubrkwall173/>
<brkwall218>
<x>22.000000<x/>
<y>14.000000<y/>
<brkwall218/>
<ubrkwall174>
<x>22.000000<x/>
<y>15.000000<y/>
<ubrkwall174/>
<ubrkwall175>
<x>22.000000<x/>
<y>16.000000<y/>
<ubrkwall175/>
<ubrkwall176>
<x>22.000000<x/>
<y>17.000000<y/>
<ubrkwall176/>
<brkwall219>
<x>22.000000<x/>
<y>18.000000<y/>
<brkwall219/>
<brkwall220>
<x>22.000000<x/>
<y>19.000000<y/>
<brkwall220/>
<ubrkwall177>
<x>22.000000<x/>
<y>20.000000<y/>
<ubrkwall177/>
<ubrkwall178>
<x>22.000000<x/>
<y>21.000000<y/>
<ubrkwall178/>
<floor209>
<x>22.000000<x/>
<y>22.000000<y/>
<floor209/>
<brkwall221>
<x>22.000000<x/>
<y>23.000000<y/>
<brkwall221/>
<ubrkwall179>
<x>22.000000<x/>
<y>24.000000<y/>
<ubrkwall179/>
<brkwall222>
<x>22.000000<x/>
<y>25.000000<y/>
<brkwall222/>
<floor210>
<x>22.000000<x/>
<y>26.000000<y/>
<floor210/>
<brkwall223>
<x>22.000000<x/>
<y>27.000000<y/>
<brkwall223/>
<floor211>
<x>22.000000<x/>
<y>28.000000<y/>
<floor211/>
<mapwall73>
<x>22.000000<x/>
<y>29.000000<y/>
<mapwall73/>
<mapwall74>
<x>23.000000<x/>
<y>0.000000<y/>
<mapwall74/>
<brkwall224>
<x>23.000000<x/>
<y>1.000000<y/>
<brkwall224/>
<ubrkwall180>
<x>23.000000<x/>
<y>2.000000<y/>
<ubrkwall180/>
<brkwall225>
<x>23.000000<x/>
<y>3.000000<y/>
<brkwall225/>
<ubrkwall181>
<x>23.000000<x/>
<y>4.000000<y/>
<ubrkwall181/>
<ubrkwall182>
<x>23.000000<x/>
<y>5.000000<y/>
<ubrkwall182/>
<ubrkwall183>
<x>23.000000<x/>
<y>6.000000<y/>
<ubrkwall183/>
<brkwall226>
<x>23.000000<x/>
<y>7.000000<y/>
<brkwall226/>
<brkwall227>
<x>23.000000<x/>
<y>8.000000<y/>
<brkwall227/>
<floor212>
<x>23.000000<x/>
<y>9.000000<y/>
<floor212/>
<ubrkwall184>
<x>23.000000<x/>
<y>10.000000<y/>
<ubrkwall184/>
<brkwall228>
<x>23.000000<x/>
<y>11.000000<y/>
<brkwall228/>
<floor213>
<x>23.000000<x/>
<y>12.000000<y/>
<floor213/>
<ubrkwall185>
<x>23.000000<x/>
<y>13.000000<y/>
<ubrkwall185/>
<ubrkwall186>
<x>23.000000<x/>
<y>14.000000<y/>
<ubrkwall186/>
<brkwall229>
<x>23.000000<x/>
<y>15.000000<y/>
<brkwall229/>
<ubrkwall187>
<x>23.000000<x/>
<y>16.000000<y/>
<ubrkwall187/>
<brkwall230>
<x>23.000000<x/>
<y>17.000000<y/>
<brkwall230/>
<brkwall231>
<x>23.000000<x/>
<y>18.000000<y/>
<brkwall231/>
<brkwall232>
<x>23.000000<x/>
<y>19.000000<y/>
<brkwall232/>
<brkwall233>
<x>23.000000<x/>
<y>20.000000<y/>
<brkwall233/>
<brkwall234>
<x>23.000000<x/>
<y>21.000000<y/>
<brkwall234/>
<brkwall235>
<x>23.000000<x/>
<y>22.000000<y/>
<brkwall235/>
<brkwall236>
<x>23.000000<x/>
<y>23.000000<y/>
<brkwall236/>
<brkwall237>
<x>23.000000<x/>
<y>24.000000<y/>
<brkwall237/>
<floor214>
<x>23.000000<x/>
<y>25.000000<y/>
<floor214/>
<floor215>
<x>23.000000<x/>
<y>26.000000<y/>
<floor215/>
<brkwall238>
<x>23.000000<x/>
<y>27.000000<y/>
<brkwall238/>
<floor216>
<x>23.000000<x/>
<y>28.000000<y/>
<floor216/>
<mapwall75>
<x>23.000000<x/>
<y>29.000000<y/>
<mapwall75/>
<mapwall76>
<x>24.000000<x/>
<y>0.000000<y/>
<mapwall76/>
<floor217>
<x>24.000000<x/>
<y>1.000000<y/>
<floor217/>
<floor218>
<x>24.000000<x/>
<y>2.000000<y/>
<floor218/>
<brkwall239>
<x>24.000000<x/>
<y>3.000000<y/>
<brkwall239/>
<ubrkwall188>
<x>24.000000<x/>
<y>4.000000<y/>
<ubrkwall188/>
<floor219>
<x>24.000000<x/>
<y>5.000000<y/>
<floor219/>
<brkwall240>
<x>24.000000<x/>
<y>6.000000<y/>
<brkwall240/>
<brkwall241>
<x>24.000000<x/>
<y>7.000000<y/>
<brkwall241/>
<ubrkwall189>
<x>24.000000<x/>
<y>8.000000<y/>
<ubrkwall189/>
<ubrkwall190>
<x>24.000000<x/>
<y>9.000000<y/>
<ubrkwall190/>
<brkwall242>
<x>24.000000<x/>
<y>10.000000<y/>
<brkwall242/>
<floor220>
<x>24.000000<x/>
<y>11.000000<y/>
<floor220/>
<floor221>
<x>24.000000<x/>
<y>12.000000<y/>
<floor221/>
<floor222>
<x>24.000000<x/>
<y>13.000000<y/>
<floor222/>
<brkwall243>
<x>24.000000<x/>
<y>14.000000<y/>
<brkwall243/>
<ubrkwall191>
<x>24.000000<x/>
<y>15.000000<y/>
<ubrkwall191/>
<ubrkwall192>
<x>24.000000<x/>
<y>16.000000<y/>
<ubrkwall192/>
<floor223>
<x>24.000000<x/>
<y>17.000000<y/>
<floor223/>
<brkwall244>
<x>24.000000<x/>
<y>18.000000<y/>
<brkwall244/>
<brkwall245>
<x>24.000000<x/>
<y>19.000000<y/>
<brkwall245/>
<floor224>
<x>24.000000<x/>
<y>20.000000<y/>
<floor224/>
<ubrkwall193>
<x>24.000000<x/>
<y>21.000000<y/>
<ubrkwall193/>
<brkwall246>
<x>24.000000<x/>
<y>22.000000<y/>
<brkwall246/>
<ubrkwall194>
<x>24.000000<x/>
<y>23.000000<y/>
<ubrkwall194/>
<brkwall247>
<x>24.000000<x/>
<y>24.000000<y/>
<brkwall247/>
<ubrkwall195>
<x>24.000000<x/>
<y>25.000000<y/>
<ubrkwall195/>
<floor225>
<x>24.000000<x/>
<y>26.000000<y/>
<floor225/>
<ubrkwall196>
<x>24.000000<x/>
<y>27.000000<y/>
<ubrkwall196/>
<floor226>
<x>24.000000<x/>
<y>28.000000<y/>
<floor226/>
<mapwall77>
<x>24.000000<x/>
<y>29.000000<y/>
<mapwall77/>
<mapwall78>
<x>25.000000<x/>
<y>0.000000<y/>
<mapwall78/>
<floor227>
<x>25.000000<x/>
<y>1.000000<y/>
<floor227/>
<floor228>
<x>25.000000<x/>
<y>2.000000<y/>
<floor228/>
<floor229>
<x>25.000000<x/>
<y>3.000000<y/>
<floor229/>
<ubrkwall197>
<x>25.000000<x/>
<y>4.000000<y/>
<ubrkwall197/>
<brkwall248>
<x>25.000000<x/>
<y>5.000000<y/>
<brkwall248/>
<brkwall249>
<x>25.000000<x/>
<y>6.000000<y/>
<brkwall249/>
<floor230>
<x>25.000000<x/>
<y>7.000000<y/>
<floor230/>
<brkwall250>
<x>25.000000<x/>
<y>8.000000<y/>
<brkwall250/>
<brkwall251>
<x>25.000000<x/>
<y>9.000000<y/>
<brkwall251/>
<floor231>
<x>25.000000<x/>
<y>10.000000<y/>
<floor231/>
<ubrkwall198>
<x>25.000000<x/>
<y>11.000000<y/>
<ubrkwall198/>
<floor232>
<x>25.000000<x/>
<y>12.000000<y/>
<floor232/>
<floor233>
<x>25.000000<x/>
<y>13.000000<y/>
<floor233/>
<floor234>
<x>25.000000<x/>
<y>14.000000<y/>
<floor234/>
<floor235>
<x>25.000000<x/>
<y>15.000000<y/>
<floor235/>
<ubrkwall199>
<x>25.000000<x/>
<y>16.000000<y/>
<ubrkwall199/>
<brkwall252>
<x>25.000000<x/>
<y>17.000000<y/>
<brkwall252/>
<brkwall253>
<x>25.000000<x/>
<y>18.000000<y/>
<brkwall253/>
<floor236>
<x>25.000000<x/>
<y>19.000000<y/>
<floor236/>
<brkwall254>
<x>25.000000<x/>
<y>20.000000<y/>
<brkwall254/>
<floor237>
<x>25.000000<x/>
<y>21.000000<y/>
<floor237/>
<floor238>
<x>25.000000<x/>
<y>22.000000<y/>
<floor238/>
<ubrkwall200>
<x>25.000000<x/>
<y>23.000000<y/>
<ubrkwall200/>
<ubrkwall201>
<x>25.000000<x/>
<y>24.000000<y/>
<ubrkwall201/>
<ubrkwall202>
<x>25.000000<x/>
<y>25.000000<y/>
<ubrkwall202/>
<floor239>
<x>25.000000<x/>
<y>26.000000<y/>
<floor239/>
<ubrkwall203>
<x>25.000000<x/>
<y>27.000000<y/>
<ubrkwall203/>
<floor240>
<x>25.000000<x/>
<y>28.000000<y/>
<floor240/>
<mapwall79>
<x>25.000000<x/>
<y>29.000000<y/>
<mapwall79/>
<mapwall80>
<x>26.000000<x/>
<y>0.000000<y/>
<mapwall80/>
<brkwall255>
<x>26.000000<x/>
<y>1.000000<y/>
<brkwall255/>
<ubrkwall204>
<x>26.000000<x/>
<y>2.000000<y/>
<ubrkwall204/>
<brkwall256>
<x>26.000000<x/>
<y>3.000000<y/>
<brkwall256/>
<floor241>
<x>26.000000<x/>
<y>4.000000<y/>
<floor241/>
<ubrkwall205>
<x>26.000000<x/>
<y>5.000000<y/>
<ubrkwall205/>
<floor242>
<x>26.000000<x/>
<y>6.000000<y/>
<floor242/>
<ubrkwall206>
<x>26.000000<x/>
<y>7.000000<y/>
<ubrkwall206/>
<brkwall257>
<x>26.000000<x/>
<y>8.000000<y/>
<brkwall257/>
<brkwall258>
<x>26.000000<x/>
<y>9.000000<y/>
<brkwall258/>
<brkwall259>
<x>26.000000<x/>
<y>10.000000<y/>
<brkwall259/>
<brkwall260>
<x>26.000000<x/>
<y>11.000000<y/>
<brkwall260/>
<floor243>
<x>26.000000<x/>
<y>12.000000<y/>
<floor243/>
<floor244>
<x>26.000000<x/>
<y>13.000000<y/>
<floor244/>
<floor245>
<x>26.000000<x/>
<y>14.000000<y/>
<floor245/>
<floor246>
<x>26.000000<x/>
<y>15.000000<y/>
<floor246/>
<ubrkwall207>
<x>26.000000<x/>
<y>16.000000<y/>
<ubrkwall207/>
<brkwall261>
<x>26.000000<x/>
<y>17.000000<y/>
<brkwall261/>
<ubrkwall208>
<x>26.000000<x/>
<y>18.000000<y/>
<ubrkwall208/>
<ubrkwall209>
<x>26.000000<x/>
<y>19.000000<y/>
<ubrkwall209/>
<brkwall262>
<x>26.000000<x/>
<y>20.000000<y/>
<brkwall262/>
<ubrkwall210>
<x>26.000000<x/>
<y>21.000000<y/>
<ubrkwall210/>
<brkwall263>
<x>26.000000<x/>
<y>22.000000<y/>
<brkwall263/>
<brkwall264>
<x>26.000000<x/>
<y>23.000000<y/>
<brkwall264/>
<brkwall265>
<x>26.000000<x/>
<y>24.000000<y/>
<brkwall265/>
<ubrkwall211>
<x>26.000000<x/>
<y>25.000000<y/>
<ubrkwall211/>
<floor247>
<x>26.000000<x/>
<y>26.000000<y/>
<floor247/>
<brkwall266>
<x>26.000000<x/>
<y>27.000000<y/>
<brkwall266/>
<floor248>
<x>26.000000<x/>
<y>28.000000<y/>
<floor248/>
<mapwall81>
<x>26.000000<x/>
<y>29.000000<y/>
<mapwall81/>
<mapwall82>
<x>27.000000<x/>
<y>0.000000<y/>
<mapwall82/>
<brkwall267>
<x>27.000000<x/>
<y>1.000000<y/>
<brkwall267/>
<ubrkwall212>
<x>27.000000<x/>
<y>2.000000<y/>
<ubrkwall212/>
<brkwall268>
<x>27.000000<x/>
<y>3.000000<y/>
<brkwall268/>
<floor249>
<x>27.000000<x/>
<y>4.000000<y/>
<floor249/>
<brkwall269>
<x>27.000000<x/>
<y>5.000000<y/>
<brkwall269/>
<brkwall270>
<x>27.000000<x/>
<y>6.000000<y/>
<brkwall270/>
<ubrkwall213>
<x>27.000000<x/>
<y>7.000000<y/>
<ubrkwall213/>
<brkwall271>
<x>27.000000<x/>
<y>8.000000<y/>
<brkwall271/>
<floor250>
<x>27.000000<x/>
<y>9.000000<y/>
<floor250/>
<ubrkwall214>
<x>27.000000<x/>
<y>10.000000<y/>
<ubrkwall214/>
<ubrkwall215>
<x>27.000000<x/>
<y>11.000000<y/>
<ubrkwall215/>
<floor251>
<x>27.000000<x/>
<y>12.000000<y/>
<floor251/>
<floor252>
<x>27.000000<x/>
<y>13.000000<y/>
<floor252/>
<floor253>
<x>27.000000<x/>
<y>14.000000<y/>
<floor253/>
<ubrkwall216>
<x>27.000000<x/>
<y>15.000000<y/>
<ubrkwall216/>
<ubrkwall217>
<x>27.000000<x/>
<y>16.000000<y/>
<ubrkwall217/>
<floor254>
<x>27.000000<x/>
<y>17.000000<y/>
<floor254/>
<ubrkwall218>
<x>27.000000<x/>
<y>18.000000<y/>
<ubrkwall218/>
<floor255>
<x>27.000000<x/>
<y>19.000000<y/>
<floor255/>
<floor256>
<x>27.000000<x/>
<y>20.000000<y/>
<floor256/>
<brkwall272>
<x>27.000000<x/>
<y>21.000000<y/>
<brkwall272/>
<floor257>
<x>27.000000<x/>
<y>22.000000<y/>
<floor257/>
<floor258>
<x>27.000000<x/>
<y>23.000000<y/>
<floor258/>
<ubrkwall219>
<x>27.000000<x/>
<y>24.000000<y/>
<ubrkwall219/>
<floor259>
<x>27.000000<x/>
<y>25.000000<y/>
<floor259/>
<ubrkwall220>
<x>27.000000<x/>
<y>26.000000<y/>
<ubrkwall220/>
<ubrkwall221>
<x>27.000000<x/>
<y>27.000000<y/>
<ubrkwall221/>
<brkwall273>
<x>27.000000<x/>
<y>28.000000<y/>
<brkwall273/>
<mapwall83>
<x>27.000000<x/>
<y>29.000000<y/>
<mapwall83/>
<mapwall84>
<x>28.000000<x/>
<y>0.000000<y/>
<mapwall84/>
<brkwall274>
<x>28.000000<x/>
<y>1.000000<y/>
<brkwall274/>
<brkwall275>
<x>28.000000<x/>
<y>2.000000<y/>
<brkwall275/>
<floor260>
<x>28.000000<x/>
<y>3.000000<y/>
<floor260/>
<floor261>
<x>28.000000<x/>
<y>4.000000<y/>
<floor261/>
<brkwall276>
<x>28.000000<x/>
<y>5.000000<y/>
<brkwall276/>
<floor262>
<x>28.000000<x/>
<y>6.000000<y/>
<floor262/>
<floor263>
<x>28.000000<x/>
<y>7.000000<y/>
<floor263/>
<floor264>
<x>28.000000<x/>
<y>8.000000<y/>
<floor264/>
<floor265>
<x>28.000000<x/>
<y>9.000000<y/>
<floor265/>
<floor266>
<x>28.000000<x/>
<y>10.000000<y/>
<floor266/>
<brkwall277>
<x>28.000000<x/>
<y>11.000000<y/>
<brkwall277/>
<floor267>
<x>28.000000<x/>
<y>12.000000<y/>
<floor267/>
<brkwall278>
<x>28.000000<x/>
<y>13.000000<y/>
<brkwall278/>
<brkwall279>
<x>28.000000<x/>
<y>14.000000<y/>
<brkwall279/>
<floor268>
<x>28.000000<x/>
<y>15.000000<y/>
<floor268/>
<brkwall280>
<x>28.000000<x/>
<y>16.000000<y/>
<brkwall280/>
<floor269>
<x>28.000000<x/>
<y>17.000000<y/>
<floor269/>
<brkwall281>
<x>28.000000<x/>
<y>18.000000<y/>
<brkwall281/>
<floor270>
<x>28.000000<x/>
<y>19.000000<y/>
<floor270/>
<brkwall282>
<x>28.000000<x/>
<y>20.000000<y/>
<brkwall282/>
<floor271>
<x>28.000000<x/>
<y>21.000000<y/>
<floor271/>
<brkwall283>
<x>28.000000<x/>
<y>22.000000<y/>
<brkwall283/>
<floor272>
<x>28.000000<x/>
<y>23.000000<y/>
<floor272/>
<brkwall284>
<x>28.000000<x/>
<y>24.000000<y/>
<brkwall284/>
<brkwall285>
<x>28.000000<x/>
<y>25.000000<y/>
<brkwall285/>
<floor273>
<x>28.000000<x/>
<y>26.000000<y/>
<floor273/>
<brkwall286>
<x>28.000000<x/>
<y>27.000000<y/>
<brkwall286/>
<floor274>
<x>28.000000<x/>
<y>28.000000<y/>
<floor274/>
<mapwall85>
<x>28.000000<x/>
<y>29.000000<y/>
<mapwall85/>
<mapwall86>
<x>29.000000<x/>
<y>0.000000<y/>
<mapwall86/>
<mapwall87>
<x>29.000000<x/>
<y>1.000000<y/>
<mapwall87/>
<mapwall88>
<x>29.000000<x/>
<y>2.000000<y/>
<mapwall88/>
<mapwall89>
<x>29.000000<x/>
<y>3.000000<y/>
<mapwall89/>
<mapwall90>
<x>29.000000<x/>
<y>4.000000<y/>
<mapwall90/>
<mapwall91>
<x>29.000000<x/>
<y>5.000000<y/>
<mapwall91/>
<mapwall92>
<x>29.000000<x/>
<y>6.000000<y/>
<mapwall92/>
<mapwall93>
<x>29.000000<x/>
<y>7.000000<y/>
<mapwall93/>
<mapwall94>
<x>29.000000<x/>
<y>8.000000<y/>
<mapwall94/>
<mapwall95>
<x>29.000000<x/>
<y>9.000000<y/>
<mapwall95/>
<mapwall96>
<x>29.000000<x/>
<y>10.000000<y/>
<mapwall96/>
<mapwall97>
<x>29.000000<x/>
<y>11.000000<y/>
<mapwall97/>
<mapwall98>
<x>29.000000<x/>
<y>12.000000<y/>
<mapwall98/>
<mapwall99>
<x>29.000000<x/>
<y>13.000000<y/>
<mapwall99/>
<mapwall100>
<x>29.000000<x/>
<y>14.000000<y/>
<mapwall100/>
<mapwall101>
<x>29.000000<x/>
<y>15.000000<y/>
<mapwall101/>
<mapwall102>
<x>29.000000<x/>
<y>16.000000<y/>
<mapwall102/>
<mapwall103>
<x>29.000000<x/>
<y>17.000000<y/>
<mapwall103/>
<mapwall104>
<x>29.000000<x/>
<y>18.000000<y/>
<mapwall104/>
<mapwall105>
<x>29.000000<x/>
<y>19.000000<y/>
<mapwall105/>
<mapwall106>
<x>29.000000<x/>
<y>20.000000<y/>
<mapwall106/>
<mapwall107>
<x>29.000000<x/>
<y>21.000000<y/>
<mapwall107/>
<mapwall108>
<x>29.000000<x/>
<y>22.000000<y/>
<mapwall108/>
<mapwall109>
<x>29.000000<x/>
<y>23.000000<y/>
<mapwall109/>
<mapwall110>
<x>29.000000<x/>
<y>24.000000<y/>
<mapwall110/>
<mapwall111>
<x>29.000000<x/>
<y>25.000000<y/>
<mapwall111/>
<mapwall112>
<x>29.000000<x/>
<y>26.000000<y/>
<mapwall112/>
<mapwall113>
<x>29.000000<x/>
<y>27.000000<y/>
<mapwall113/>
<mapwall114>
<x>29.000000<x/>
<y>28.000000<y/>
<mapwall114/>
<mapwall115>
<x>29.000000<x/>
<y>29.000000<y/>
<mapwall115/>
<player0>
<x>15.000000<x/>
<y>22.000000<y/>
<player0/>
<player1>
<x>26.000000<x/>
<y>13.000000<y/>
<player1/>
<player2>
<x>15.000000<x/>
<y>22.000000<y/>
<player2/>
<player3>
<x>26.000000<x/>
<y>13.000000<y/>
<player3/>
